streamlit_confetti/__init__.py
streamlit_confetti/frontend/build/asset-manifest.json
streamlit_confetti/frontend/build/bootstrap.min.css
streamlit_confetti/frontend/build/index.html
streamlit_confetti/frontend/build/precache-manifest.a4c64caa0fe09ac3e6a8cffbddb811ee.js
streamlit_confetti/frontend/build/service-worker.js
streamlit_confetti/frontend/build/static/js/2.bba2bda8.chunk.js
streamlit_confetti/frontend/build/static/js/2.bba2bda8.chunk.js.LICENSE.txt
streamlit_confetti/frontend/build/static/js/2.bba2bda8.chunk.js.map
streamlit_confetti/frontend/build/static/js/main.cc7c0cde.chunk.js
streamlit_confetti/frontend/build/static/js/main.cc7c0cde.chunk.js.map
streamlit_confetti/frontend/build/static/js/runtime-main.4f5a3da5.js
streamlit_confetti/frontend/build/static/js/runtime-main.4f5a3da5.js.map
streamlit_confetti-0.1.0.dist-info/LICENSE
streamlit_confetti-0.1.0.dist-info/METADATA
streamlit_confetti-0.1.0.dist-info/WHEEL
streamlit_confetti-0.1.0.dist-info/top_level.txt
streamlit_confetti-0.1.0.dist-info/RECORD
