Metadata-Version: 2.1
Name: streamlit-confetti
Version: 0.1.0
Summary: Streamlit Component wrapper on top of JSConfetti library
Home-page: 
Author: Ivan Sorokin
Author-email: i.sorok1n@icloud.com
Requires-Python: >=3.6
License-File: LICENSE
Requires-Dist: streamlit (>=0.63)
